{
  "captured_at": "2026-04-13T10:25:05.106606+00:00",
  "payload": {
    "success": true,
    "message": "",
    "data": [
      {
        "nombreAgrupacionPolitica": "PERÚ MODERNO",
        "codigoAgrupacionPolitica": 4,
        "nombreCandidato": "CARLOS ERNESTO JAICO CARRANZA",
        "dniCandidato": "06529088",
        "totalVotosValidos": 4901,
        "porcentajeVotosValidos": 0.053,
        "porcentajeVotosEmitidos": 0.046
      },
      {
        "nombreAgrupacionPolitica": "PARTIDO DE LOS TRABAJADORES Y EMPRENDEDORES PTE - PERÚ",
        "codigoAgrupacionPolitica": 15,
        "nombreCandidato": "NAPOLEON BECERRA GARCIA",
        "dniCandidato": "08058852",
        "totalVotosValidos": 5937,
        "porcentajeVotosValidos": 0.065,
        "porcentajeVotosEmitidos": 0.056
      },
      {
        "nombreAgrupacionPolitica": "PARTIDO POLÍTICO PRIN",
        "codigoAgrupacionPolitica": 30,
        "nombreCandidato": "WALTER GILMER CHIRINOS PURIZAGA",
        "dniCandidato": "18870364",
        "totalVotosValidos": 7014,
        "porcentajeVotosValidos": 0.077,
        "porcentajeVotosEmitidos": 0.066
      },
      {
        "nombreAgrupacionPolitica": "SALVEMOS AL PERÚ",
        "codigoAgrupacionPolitica": 36,
        "nombreCandidato": "ANTONIO ORTIZ VILLANO",
        "dniCandidato": "08587486",
        "totalVotosValidos": 7021,
        "porcentajeVotosValidos": 0.077,
        "porcentajeVotosEmitidos": 0.066
      },
      {
        "nombreAgrupacionPolitica": "PARTIDO DEMOCRATICO FEDERAL",
        "codigoAgrupacionPolitica": 19,
        "nombreCandidato": "ARMANDO JOAQUIN MASSE FERNANDEZ",
        "dniCandidato": "08255194",
        "totalVotosValidos": 10522,
        "porcentajeVotosValidos": 0.115,
        "porcentajeVotosEmitidos": 0.099
      },
      {
        "nombreAgrupacionPolitica": "FE EN EL PERÚ",
        "codigoAgrupacionPolitica": 5,
        "nombreCandidato": "ALVARO GONZALO PAZ DE LA BARRA FREIGEIRO",
        "dniCandidato": "41904418",
        "totalVotosValidos": 10698,
        "porcentajeVotosValidos": 0.117,
        "porcentajeVotosEmitidos": 0.1
      },
      {
        "nombreAgrupacionPolitica": "FUERZA Y LIBERTAD",
        "codigoAgrupacionPolitica": 9,
        "nombreCandidato": "FIORELLA GIANNINA MOLINELLI ARISTONDO",
        "dniCandidato": "25681995",
        "totalVotosValidos": 14096,
        "porcentajeVotosValidos": 0.154,
        "porcentajeVotosEmitidos": 0.132
      },
      {
        "nombreAgrupacionPolitica": "PARTIDO POLÍTICO PERÚ ACCIÓN",
        "codigoAgrupacionPolitica": 28,
        "nombreCandidato": "FRANCISCO ERNESTO DIEZ-CANSECO TÁVARA",
        "dniCandidato": "08263758",
        "totalVotosValidos": 15636,
        "porcentajeVotosValidos": 0.171,
        "porcentajeVotosEmitidos": 0.147
      },
      {
        "nombreAgrupacionPolitica": "AVANZA PAÍS - PARTIDO DE INTEGRACIÓN SOCIAL",
        "codigoAgrupacionPolitica": 7,
        "nombreCandidato": "JOSE DANIEL WILLIAMS ZAPATA",
        "dniCandidato": "43287528",
        "totalVotosValidos": 17707,
        "porcentajeVotosValidos": 0.193,
        "porcentajeVotosEmitidos": 0.166
      },
      {
        "nombreAgrupacionPolitica": "LIBERTAD POPULAR",
        "codigoAgrupacionPolitica": 11,
        "nombreCandidato": "RAFAEL JORGE BELAUNDE LLOSA",
        "dniCandidato": "10219647",
        "totalVotosValidos": 22067,
        "porcentajeVotosValidos": 0.241,
        "porcentajeVotosEmitidos": 0.207
      },
      {
        "nombreAgrupacionPolitica": "PARTIDO DEMÓCRATA VERDE",
        "codigoAgrupacionPolitica": 18,
        "nombreCandidato": "ALEX GONZALES CASTILLO",
        "dniCandidato": "09307547",
        "totalVotosValidos": 29106,
        "porcentajeVotosValidos": 0.318,
        "porcentajeVotosEmitidos": 0.273
      },
      {
        "nombreAgrupacionPolitica": "PROGRESEMOS",
        "codigoAgrupacionPolitica": 34,
        "nombreCandidato": "PAUL DAVIS JAIMES BLANCO",
        "dniCandidato": "40139245",
        "totalVotosValidos": 34517,
        "porcentajeVotosValidos": 0.377,
        "porcentajeVotosEmitidos": 0.324
      },
      {
        "nombreAgrupacionPolitica": "PARTIDO POLÍTICO INTEGRIDAD DEMOCRÁTICA",
        "codigoAgrupacionPolitica": 26,
        "nombreCandidato": "WOLFGANG MARIO GROZO COSTA",
        "dniCandidato": "07260881",
        "totalVotosValidos": 38857,
        "porcentajeVotosValidos": 0.424,
        "porcentajeVotosEmitidos": 0.365
      },
      {
        "nombreAgrupacionPolitica": "PARTIDO POLÍTICO NACIONAL PERÚ LIBRE",
        "codigoAgrupacionPolitica": 27,
        "nombreCandidato": "VLADIMIR ROY CERRON ROJAS",
        "dniCandidato": "06466585",
        "totalVotosValidos": 43524,
        "porcentajeVotosValidos": 0.475,
        "porcentajeVotosEmitidos": 0.408
      },
      {
        "nombreAgrupacionPolitica": "UNIDAD NACIONAL",
        "codigoAgrupacionPolitica": 38,
        "nombreCandidato": "ROBERTO ENRIQUE CHIABRA LEON",
        "dniCandidato": "40728264",
        "totalVotosValidos": 43871,
        "porcentajeVotosValidos": 0.479,
        "porcentajeVotosEmitidos": 0.412
      },
      {
        "nombreAgrupacionPolitica": "UN CAMINO DIFERENTE",
        "codigoAgrupacionPolitica": 37,
        "nombreCandidato": "ROSARIO DEL PILAR FERNANDEZ BAZAN",
        "dniCandidato": "18141156",
        "totalVotosValidos": 46822,
        "porcentajeVotosValidos": 0.511,
        "porcentajeVotosEmitidos": 0.439
      },
      {
        "nombreAgrupacionPolitica": "PARTIDO MORADO",
        "codigoAgrupacionPolitica": 22,
        "nombreCandidato": "MESIAS ANTONIO GUEVARA AMASIFUEN",
        "dniCandidato": "09871134",
        "totalVotosValidos": 48180,
        "porcentajeVotosValidos": 0.526,
        "porcentajeVotosEmitidos": 0.452
      },
      {
        "nombreAgrupacionPolitica": "PARTIDO DEMÓCRATA UNIDO PERÚ",
        "codigoAgrupacionPolitica": 17,
        "nombreCandidato": "CHARLIE CARRASCO SALAZAR",
        "dniCandidato": "40799023",
        "totalVotosValidos": 55657,
        "porcentajeVotosValidos": 0.607,
        "porcentajeVotosEmitidos": 0.522
      },
      {
        "nombreAgrupacionPolitica": "ALIANZA ELECTORAL VENCEREMOS",
        "codigoAgrupacionPolitica": 3,
        "nombreCandidato": "RONALD DARWIN ATENCIO SOTOMAYOR",
        "dniCandidato": "41373494",
        "totalVotosValidos": 60104,
        "porcentajeVotosValidos": 0.656,
        "porcentajeVotosEmitidos": 0.564
      },
      {
        "nombreAgrupacionPolitica": "PARTIDO POLÍTICO PERÚ PRIMERO",
        "codigoAgrupacionPolitica": 29,
        "nombreCandidato": "MARIO ENRIQUE VIZCARRA CORNEJO",
        "dniCandidato": "04411300",
        "totalVotosValidos": 66638,
        "porcentajeVotosValidos": 0.727,
        "porcentajeVotosEmitidos": 0.625
      },
      {
        "nombreAgrupacionPolitica": "PARTIDO PATRIÓTICO DEL PERÚ",
        "codigoAgrupacionPolitica": 24,
        "nombreCandidato": "HERBERT CALLER GUTIERREZ",
        "dniCandidato": "43409673",
        "totalVotosValidos": 71998,
        "porcentajeVotosValidos": 0.786,
        "porcentajeVotosEmitidos": 0.676
      },
      {
        "nombreAgrupacionPolitica": "PARTIDO DEMOCRÁTICO SOMOS PERÚ",
        "codigoAgrupacionPolitica": 20,
        "nombreCandidato": "GEORGE PATRICK FORSYTH SOMMER",
        "dniCandidato": "41265978",
        "totalVotosValidos": 73025,
        "porcentajeVotosValidos": 0.797,
        "porcentajeVotosEmitidos": 0.685
      },
      {
        "nombreAgrupacionPolitica": "ALIANZA PARA EL PROGRESO",
        "codigoAgrupacionPolitica": 1,
        "nombreCandidato": "CESAR ACUÑA PERALTA",
        "dniCandidato": "17903382",
        "totalVotosValidos": 78419,
        "porcentajeVotosValidos": 0.856,
        "porcentajeVotosEmitidos": 0.736
      },
      {
        "nombreAgrupacionPolitica": "PARTIDO APRISTA PERUANO",
        "codigoAgrupacionPolitica": 12,
        "nombreCandidato": "PITTER ENRIQUE VALDERRAMA PEÑA",
        "dniCandidato": "43632186",
        "totalVotosValidos": 83496,
        "porcentajeVotosValidos": 0.911,
        "porcentajeVotosEmitidos": 0.784
      },
      {
        "nombreAgrupacionPolitica": "PARTIDO POLÍTICO COOPERACIÓN POPULAR",
        "codigoAgrupacionPolitica": 25,
        "nombreCandidato": "YONHY LESCANO ANCIETA",
        "dniCandidato": "01211014",
        "totalVotosValidos": 104539,
        "porcentajeVotosValidos": 1.141,
        "porcentajeVotosEmitidos": 0.981
      },
      {
        "nombreAgrupacionPolitica": "PODEMOS PERÚ",
        "codigoAgrupacionPolitica": 32,
        "nombreCandidato": "JOSE LEON LUNA GALVEZ",
        "dniCandidato": "07246887",
        "totalVotosValidos": 113334,
        "porcentajeVotosValidos": 1.237,
        "porcentajeVotosEmitidos": 1.064
      },
      {
        "nombreAgrupacionPolitica": "PARTIDO FRENTE DE LA ESPERANZA 2021",
        "codigoAgrupacionPolitica": 21,
        "nombreCandidato": "LUIS FERNANDO OLIVERA VEGA",
        "dniCandidato": "06280714",
        "totalVotosValidos": 164432,
        "porcentajeVotosValidos": 1.795,
        "porcentajeVotosEmitidos": 1.543
      },
      {
        "nombreAgrupacionPolitica": "PARTIDO SICREO",
        "codigoAgrupacionPolitica": 31,
        "nombreCandidato": "ALFONSO CARLOS ESPA Y GARCES-ALVEAR",
        "dniCandidato": "10266270",
        "totalVotosValidos": 343263,
        "porcentajeVotosValidos": 3.747,
        "porcentajeVotosEmitidos": 3.221
      },
      {
        "nombreAgrupacionPolitica": "PRIMERO LA GENTE – COMUNIDAD, ECOLOGÍA, LIBERTAD Y PROGRESO",
        "codigoAgrupacionPolitica": 33,
        "nombreCandidato": "MARIA SOLEDAD PEREZ TELLO",
        "dniCandidato": "07867789",
        "totalVotosValidos": 362598,
        "porcentajeVotosValidos": 3.958,
        "porcentajeVotosEmitidos": 3.403
      },
      {
        "nombreAgrupacionPolitica": "JUNTOS POR EL PERÚ",
        "codigoAgrupacionPolitica": 10,
        "nombreCandidato": "ROBERTO HELBERT SANCHEZ PALOMINO",
        "dniCandidato": "16002918",
        "totalVotosValidos": 690075,
        "porcentajeVotosValidos": 7.532,
        "porcentajeVotosEmitidos": 6.476
      },
      {
        "nombreAgrupacionPolitica": "AHORA NACIÓN - AN",
        "codigoAgrupacionPolitica": 2,
        "nombreCandidato": "PABLO ALFONSO LOPEZ CHAU NAVA",
        "dniCandidato": "25331980",
        "totalVotosValidos": 693544,
        "porcentajeVotosValidos": 7.57,
        "porcentajeVotosEmitidos": 6.508
      },
      {
        "nombreAgrupacionPolitica": "PARTIDO PAÍS PARA TODOS",
        "codigoAgrupacionPolitica": 23,
        "nombreCandidato": "CARLOS GONSALO ALVAREZ LOAYZA",
        "dniCandidato": "06002034",
        "totalVotosValidos": 780515,
        "porcentajeVotosValidos": 8.519,
        "porcentajeVotosEmitidos": 7.324
      },
      {
        "nombreAgrupacionPolitica": "PARTIDO CÍVICO OBRAS",
        "codigoAgrupacionPolitica": 14,
        "nombreCandidato": "RICARDO PABLO BELMONT CASSINELLI",
        "dniCandidato": "09177250",
        "totalVotosValidos": 893588,
        "porcentajeVotosValidos": 9.753,
        "porcentajeVotosEmitidos": 8.385
      },
      {
        "nombreAgrupacionPolitica": "PARTIDO DEL BUEN GOBIERNO",
        "codigoAgrupacionPolitica": 16,
        "nombreCandidato": "JORGE NIETO MONTESINOS",
        "dniCandidato": "06506278",
        "totalVotosValidos": 1195118,
        "porcentajeVotosValidos": 13.044,
        "porcentajeVotosEmitidos": 11.215
      },
      {
        "nombreAgrupacionPolitica": "RENOVACIÓN POPULAR",
        "codigoAgrupacionPolitica": 35,
        "nombreCandidato": "RAFAEL BERNARDO LÓPEZ ALIAGA CAZORLA",
        "dniCandidato": "07845838",
        "totalVotosValidos": 1373993,
        "porcentajeVotosValidos": 14.997,
        "porcentajeVotosEmitidos": 12.894
      },
      {
        "nombreAgrupacionPolitica": "FUERZA POPULAR",
        "codigoAgrupacionPolitica": 8,
        "nombreCandidato": "KEIKO SOFIA FUJIMORI HIGUCHI",
        "dniCandidato": "10001088",
        "totalVotosValidos": 1557226,
        "porcentajeVotosValidos": 16.997,
        "porcentajeVotosEmitidos": 14.613
      }
    ]
  }
}